[
   {
      "name": "Anonymous",
      "time": "2019-09-19T19:36:20.463Z"
   },
   {
      "name": "Anonymous",
      "time": "2019-09-19T19:40:30.202Z"
   },
   {
      "name": "Anonymous",
      "time": "2019-09-19T20:06:22.481Z"
   },
   {
      "name": "Anonymous",
      "time": "2019-09-19T20:13:27.090Z"
   },
   {
      "name": "Anonymous",
      "time": "2019-09-19T20:14:06.657Z"
   },
   {
      "name": "Anonymous",
      "time": "2019-09-19T20:25:52.274Z"
   },
   {
      "name": "Anonymous",
      "time": "2019-09-19T20:34:03.478Z"
   },
   {
      "name": "Anonymous",
      "time": "2019-09-19T20:51:26.457Z"
   },
   {
      "name": "Anonymous",
      "time": "2019-09-19T20:51:40.399Z"
   },
   {
      "name": "Anonymous",
      "time": "2019-09-19T22:18:57.554Z"
   },
   {
      "name": "Anonymous",
      "time": "2019-09-19T22:19:30.337Z"
   },
   {
      "name": "Anonymous",
      "time": "2019-09-19T22:19:33.375Z"
   },
   {
      "name": "Anonymous",
      "time": "2019-09-19T22:21:41.533Z"
   },
   {
      "name": "Anonymous",
      "time": "2019-09-19T22:23:21.851Z"
   },
   {
      "name": "Anonymous",
      "time": "2019-09-19T22:31:18.220Z"
   },
   {
      "name": "Anonymous",
      "time": "2019-09-19T22:31:20.282Z"
   },
   {
      "name": "Anonymous",
      "time": "2019-09-19T22:32:06.602Z"
   },
   {
      "name": "Anonymous",
      "time": "2019-09-19T22:32:11.558Z"
   },
   {
      "name": "Anonymous",
      "time": "2019-09-19T22:38:20.165Z"
   },
   {
      "name": "Anonymous",
      "time": "2019-09-19T22:38:20.906Z"
   },
   {
      "name": "Anonymous",
      "time": "2019-09-19T22:40:16.941Z"
   },
   {
      "name": "Anonymous",
      "time": "2019-09-19T22:41:20.038Z"
   },
   {
      "name": "Anonymous",
      "time": "2019-09-19T22:46:04.017Z"
   },
   {
      "name": "Anonymous",
      "time": "2019-09-19T22:46:04.925Z"
   },
   {
      "name": "Anonymous",
      "time": "2019-09-19T22:48:34.821Z"
   },
   {
      "name": "Anonymous",
      "time": "2019-09-19T22:49:52.030Z"
   },
   {
      "name": "Anonymous",
      "time": "2019-09-19T22:49:53.254Z"
   },
   {
      "name": "Anonymous",
      "time": "2019-09-19T22:51:25.155Z"
   },
   {
      "name": "Anonymous",
      "time": "2019-09-19T22:51:26.933Z"
   },
   {
      "name": "Anonymous",
      "time": "2019-09-19T22:55:36.538Z"
   },
   {
      "name": "Anonymous",
      "time": "2019-09-19T22:55:41.855Z"
   },
   {
      "name": "Anonymous",
      "time": "2019-09-19T22:56:51.543Z"
   },
   {
      "name": "Anonymous",
      "time": "2019-09-19T23:03:47.761Z"
   },
   {
      "name": "Anonymous",
      "time": "2019-09-19T23:46:36.826Z"
   },
   {
      "name": "Anonymous",
      "time": "2019-09-20T00:08:36.536Z"
   },
   {
      "name": "Anonymous",
      "time": "2019-09-20T00:08:54.972Z"
   },
   {
      "name": "Anonymous",
      "time": "2019-09-20T00:09:47.138Z"
   },
   {
      "name": "Anonymous",
      "time": "2019-09-20T00:09:48.168Z"
   },
   {
      "name": "Anonymous",
      "time": "2019-09-20T00:10:04.259Z"
   },
   {
      "name": "Anonymous",
      "time": "2019-09-20T00:30:27.383Z"
   },
   {
      "name": "Anonymous",
      "time": "2019-09-20T00:30:28.686Z"
   },
   {
      "name": "Anonymous",
      "time": "2019-09-20T00:43:57.342Z"
   },
   {
      "name": "Anonymous",
      "time": "2019-09-20T00:44:12.013Z"
   },
   {
      "name": "Anonymous",
      "time": "2019-09-20T00:46:35.753Z"
   },
   {
      "name": "Anonymous",
      "time": "2019-09-20T00:46:56.284Z"
   },
   {
      "name": "Anonymous",
      "time": "2019-09-20T00:49:00.618Z"
   },
   {
      "name": "Anonymous",
      "time": "2019-09-20T00:49:01.557Z"
   },
   {
      "name": "Anonymous",
      "time": "2019-09-20T00:49:17.234Z"
   },
   {
      "name": "Anonymous",
      "time": "2019-09-20T00:50:02.738Z"
   },
   {
      "name": "Anonymous",
      "time": "2019-09-20T00:50:03.627Z"
   },
   {
      "name": "Anonymous",
      "time": "2019-09-20T00:50:20.674Z"
   },
   {
      "name": "Anonymous",
      "time": "2019-09-20T00:51:11.803Z"
   },
   {
      "name": "Anonymous",
      "time": "2019-09-20T00:51:12.663Z"
   },
   {
      "name": "Anonymous",
      "time": "2019-09-20T00:52:03.522Z"
   },
   {
      "name": "Anonymous",
      "time": "2019-09-20T00:52:05.025Z"
   },
   {
      "name": "Anonymous",
      "time": "2019-09-20T00:52:21.699Z"
   },
   {
      "name": "Anonymous",
      "time": "2019-09-20T00:52:45.368Z"
   },
   {
      "name": "Anonymous",
      "time": "2019-09-20T00:52:46.496Z"
   },
   {
      "name": "Anonymous",
      "time": "2019-09-20T00:52:58.106Z"
   },
   {
      "name": "Anonymous",
      "time": "2019-09-20T00:53:23.590Z"
   },
   {
      "name": "Anonymous",
      "time": "2019-09-20T00:53:30.308Z"
   },
   {
      "name": "Anonymous",
      "time": "2019-09-20T00:53:31.235Z"
   },
   {
      "name": "Anonymous",
      "time": "2019-09-20T00:53:40.564Z"
   },
   {
      "name": "Anonymous",
      "time": "2019-09-20T00:54:35.374Z"
   },
   {
      "name": "Anonymous",
      "time": "2019-09-20T00:55:13.663Z"
   },
   {
      "name": "Anonymous",
      "time": "2019-09-20T00:55:23.317Z"
   },
   {
      "name": "Anonymous",
      "time": "2019-09-20T01:05:56.120Z"
   },
   {
      "name": "Anonymous",
      "time": "2019-09-20T01:05:57.426Z"
   },
   {
      "name": "Anonymous",
      "time": "2019-09-20T01:34:11.091Z"
   },
   {
      "name": "Anonymous",
      "time": "2019-09-20T01:34:23.709Z"
   },
   {
      "name": "Anonymous",
      "time": "2019-09-20T01:34:35.865Z"
   },
   {
      "name": "Anonymous",
      "time": "2019-09-22T17:28:57.885Z"
   },
   {
      "name": "Anonymous",
      "time": "2019-09-22T17:39:20.010Z"
   },
   {
      "name": "Anonymous",
      "time": "2019-09-22T17:42:26.497Z"
   },
   {
      "name": "Anonymous",
      "time": "2019-09-22T18:07:37.462Z"
   },
   {
      "name": "Anonymous",
      "time": "2019-10-03T02:21:21.942Z"
   }
]